{"description":"This test will submit a form|This is a demo Non Angular application Protractor test","passed":true,"pending":false,"os":"Mac OS X","sessionId":"ad839336eace7495d3679fcfe0448f0d","instanceId":11423,"browser":{"name":"chrome","version":"70.0.3538.102"},"message":"Passed","browserLogs":[{"level":"WARNING","message":"http://seleniumpractise.blogspot.com/2016/09/complete-registration-form.html - This page includes a password or credit card input in a non-secure context. A warning has been added to the URL bar. For more information, see https://goo.gl/zmWq3m.","timestamp":1542487196374,"type":""}],"screenShotFile":"007700d6-0096-0054-001c-004800e000f8.png","timestamp":1542487194780,"duration":4122}
